[
    {
        "profile": "thuyduongjane",
        "url": "https://www.linkedin.com/in/thuyduongjane/",
        "name": "Thuy Duong",
        "experience": [
            {
                "position": "",
                "organisation": "",
                "organisation_profile": "https://vn.linkedin.com/company/crystal-martin-in-vietnam",
                "location": "",
                "start_time": "May 2022",
                "end_time": "present",
                "duration": "1 year 7 months"
            },
            {
                "position": "",
                "organisation": "",
                "organisation_profile": "https://www.linkedin.com/company/hanesbrands-inc-",
                "location": "",
                "start_time": "Aug 2017",
                "end_time": "Mar 2022",
                "duration": "4 years 8 months"
            },
            {
                "position": "",
                "organisation": "",
                "organisation_profile": "https://lk.linkedin.com/company/linea-aqua-la",
                "location": "",
                "start_time": "Jul 2015",
                "end_time": "Jul 2017",
                "duration": "2 years 1 month"
            }
        ],
        "education": [
            {
                "organisation": "Hung Yen University of Technology and Education",
                "organisation_profile": "",
                "course_details": "Engineer's degree Textile Garment Engineering",
                "start_time": "2011",
                "end_time": "2015"
            }
        ]
    },
    {
        "profile": "chathura-galappaththi-23492110b",
        "url": "https://www.linkedin.com/in/chathura-galappaththi-23492110b/",
        "name": "Chathura Galappaththi",
        "experience": [
            {
                "position": "Planning Executive",
                "organisation": "MAS Linea Aqua",
                "organisation_profile": "https://www.linkedin.com/company/mas-linea-aqua",
                "location": "Hanwella",
                "start_time": "Nov 2015",
                "end_time": "present",
                "duration": "8 years 1 month"
            },
            {
                "position": "Executive",
                "organisation": "JAYKAY MARKETING SERVICES (PVT.) LIMITED",
                "organisation_profile": "https://www.linkedin.com/company/jaykay-marketing-services-pvt-limited",
                "location": "",
                "start_time": "Mar 2015",
                "end_time": "Jun 2015",
                "duration": "4 months"
            }
        ],
        "education": [
            {
                "organisation": "University of Colombo",
                "organisation_profile": "",
                "course_details": "Master of Business Management",
                "start_time": "2018",
                "end_time": "2020"
            },
            {
                "organisation": "University of Ruhuna",
                "organisation_profile": "https://www.linkedin.com/school/university-of-ruhuna/",
                "course_details": "Bachelor\u2019s Degree Physical Sciences",
                "start_time": "2011",
                "end_time": "2014"
            },
            {
                "organisation": "St. Anthony's College, Wattala",
                "organisation_profile": "",
                "course_details": "GCE A/L Mathematics",
                "start_time": "1996",
                "end_time": "2009"
            }
        ]
    },
    {
        "profile": "skmn",
        "url": "https://www.linkedin.com/in/skmn/",
        "name": "Siyali Kaushala",
        "experience": [
            {
                "position": "",
                "organisation": "",
                "organisation_profile": "https://in.linkedin.com/company/arvindlimited",
                "location": "",
                "start_time": "Sep 2023",
                "end_time": "present",
                "duration": "3 months"
            },
            {
                "position": "",
                "organisation": "",
                "organisation_profile": "",
                "location": "",
                "start_time": "Oct 2020",
                "end_time": "present",
                "duration": "3 years 2 months"
            },
            {
                "position": "",
                "organisation": "",
                "organisation_profile": "https://my.linkedin.com/school/monash-university-malaysia/",
                "location": "",
                "start_time": "Feb 2016",
                "end_time": "Jun 2017",
                "duration": "1 year 5 months"
            },
            {
                "position": "",
                "organisation": "",
                "organisation_profile": "https://my.linkedin.com/company/sunwayconstruction",
                "location": "",
                "start_time": "Dec 2016",
                "end_time": "Mar 2017",
                "duration": "4 months"
            },
            {
                "position": "",
                "organisation": "",
                "organisation_profile": "",
                "location": "",
                "start_time": "Jan 2016",
                "end_time": "Feb 2016",
                "duration": "2 months"
            },
            {
                "position": "",
                "organisation": "",
                "organisation_profile": "",
                "location": "",
                "start_time": "Jun 2015",
                "end_time": "Jul 2015",
                "duration": "2 months"
            },
            {
                "position": "",
                "organisation_profile": "https://lk.linkedin.com/company/mas-kreeda",
                "location": "",
                "start_time": "Feb 2022",
                "end_time": "Jul 2023",
                "duration": "1 year 6 months"
            },
            {
                "position": "",
                "organisation_profile": "https://lk.linkedin.com/company/mas-kreeda",
                "location": "",
                "start_time": "Apr 2021",
                "end_time": "Feb 2022",
                "duration": "11 months"
            },
            {
                "position": "",
                "organisation_profile": "https://lk.linkedin.com/company/mas-kreeda",
                "location": "",
                "start_time": "Feb 2019",
                "end_time": "Apr 2021",
                "duration": "2 years 3 months"
            },
            {
                "position": "",
                "organisation_profile": "https://lk.linkedin.com/company/mas-kreeda",
                "location": "",
                "start_time": "Mar 2018",
                "end_time": "Feb 2019",
                "duration": "1 year"
            }
        ],
        "education": [
            {
                "organisation": "Monash University Malaysia",
                "organisation_profile": "https://my.linkedin.com/school/monash-university-malaysia/",
                "course_details": "Bachelors of Engineering 1 st Class Honours Mechanical Engineering",
                "start_time": "2014",
                "end_time": "2017"
            },
            {
                "organisation": "Leeds Campus of Business and Technology",
                "organisation_profile": "",
                "course_details": "BCS Certificate in IT & Diploma in IT",
                "start_time": "2012",
                "end_time": "2014"
            },
            {
                "organisation": "Leeds International School",
                "organisation_profile": "",
                "course_details": "Edexcel ALevels Mathematics",
                "start_time": "2011",
                "end_time": "2013"
            }
        ]
    }
]